<?xml version="1.0"?><ts><start>s0</start><states><state id="s3"><transition target="sX" action="epsilon" proba="1.0"></transition></state><state id="s4"><transition target="s5" action="org.w3c.dom.Node.getNodeType()" proba="0.25"></transition><transition target="sX" action="epsilon" proba="0.5"></transition><transition target="s12" action="org.w3c.dom.Node.removeChild(org.w3c.dom.Node)" proba="0.125"></transition><transition target="s17" action="org.w3c.dom.Node.appendChild(org.w3c.dom.Node)" proba="0.125"></transition></state><state id="s5"><transition target="sX" action="epsilon" proba="0.875"></transition><transition target="s1" action="org.w3c.dom.Node.getNodeName()" proba="0.125"></transition></state><state id="s6"><transition target="s13" action="org.w3c.dom.Node.getLength()" proba="0.09090909090909091"></transition><transition target="sX" action="epsilon" proba="0.5454545454545454"></transition><transition target="s14" action="org.w3c.dom.Node.removeNamedItem(java.lang.String)" proba="0.09090909090909091"></transition><transition target="s19" action="org.w3c.dom.Node.setNamedItem(org.w3c.dom.Node)" proba="0.09090909090909091"></transition><transition target="s18" action="org.w3c.dom.Node.getNamedItem(java.lang.String)" proba="0.18181818181818182"></transition></state><state id="s7"><transition target="s7" action="org.w3c.dom.Node.getTextContent()" proba="0.16666666666666666"></transition><transition target="s8" action="org.w3c.dom.Node.trim()" proba="0.16666666666666666"></transition><transition target="sX" action="epsilon" proba="0.6666666666666666"></transition></state><state id="sX"><transition target="s0" action="epsilon" proba="1.0"></transition></state><state id="s8"><transition target="s9" action="org.w3c.dom.Node.length()" proba="1.0"></transition></state><state id="s9"><transition target="sX" action="epsilon" proba="1.0"></transition></state><state id="s20"><transition target="sX" action="epsilon" proba="1.0"></transition></state><state id="s11"><transition target="sX" action="epsilon" proba="1.0"></transition></state><state id="s10"><transition target="sX" action="epsilon" proba="1.0"></transition></state><state id="s13"><transition target="sX" action="epsilon" proba="1.0"></transition></state><state id="s12"><transition target="sX" action="epsilon" proba="1.0"></transition></state><state id="s15"><transition target="sX" action="epsilon" proba="1.0"></transition></state><state id="s14"><transition target="sX" action="epsilon" proba="1.0"></transition></state><state id="s17"><transition target="sX" action="epsilon" proba="0.5"></transition><transition target="s1" action="org.w3c.dom.Node.getNodeName()" proba="0.5"></transition></state><state id="s16"><transition target="sX" action="epsilon" proba="0.6"></transition><transition target="s16" action="org.w3c.dom.Node.getChildNodes()" proba="0.2"></transition><transition target="s1" action="org.w3c.dom.Node.getNodeName()" proba="0.2"></transition></state><state id="s19"><transition target="sX" action="epsilon" proba="1.0"></transition></state><state id="s18"><transition target="sX" action="epsilon" proba="0.5"></transition><transition target="s15" action="org.w3c.dom.Node.getNodeValue()" proba="0.5"></transition></state><state id="s0"><transition target="s20" action="org.w3c.dom.Node.setNodeValue(java.lang.String)" proba="0.015151515151515152"></transition><transition target="s4" action="org.w3c.dom.Node.getParentNode()" proba="0.015151515151515152"></transition><transition target="s5" action="org.w3c.dom.Node.getNodeType()" proba="0.09090909090909091"></transition><transition target="s6" action="org.w3c.dom.Node.getAttributes()" proba="0.16666666666666666"></transition><transition target="s7" action="org.w3c.dom.Node.getTextContent()" proba="0.07575757575757576"></transition><transition target="s12" action="org.w3c.dom.Node.removeChild(org.w3c.dom.Node)" proba="0.045454545454545456"></transition><transition target="s15" action="org.w3c.dom.Node.getNodeValue()" proba="0.015151515151515152"></transition><transition target="s17" action="org.w3c.dom.Node.appendChild(org.w3c.dom.Node)" proba="0.015151515151515152"></transition><transition target="s16" action="org.w3c.dom.Node.getChildNodes()" proba="0.045454545454545456"></transition><transition target="s1" action="org.w3c.dom.Node.getNodeName()" proba="0.4696969696969697"></transition><transition target="s2" action="org.w3c.dom.Node.getOwnerDocument()" proba="0.045454545454545456"></transition></state><state id="s1"><transition target="s4" action="org.w3c.dom.Node.getParentNode()" proba="0.20588235294117646"></transition><transition target="s11" action="org.w3c.dom.Node.equals(java.lang.Object)" proba="0.08823529411764706"></transition><transition target="s10" action="org.w3c.dom.Node.setTextContent(java.lang.String)" proba="0.058823529411764705"></transition><transition target="sX" action="epsilon" proba="0.5882352941176471"></transition><transition target="s15" action="org.w3c.dom.Node.getNodeValue()" proba="0.029411764705882353"></transition><transition target="s16" action="org.w3c.dom.Node.getChildNodes()" proba="0.029411764705882353"></transition></state><state id="s2"><transition target="s3" action="org.w3c.dom.Node.getDocumentElement()" proba="0.3333333333333333"></transition><transition target="sX" action="epsilon" proba="0.6666666666666666"></transition></state></states></ts>