<?xml version="1.0"?><ts><start>s0</start><states><state id="s3"><transition target="sX" action="epsilon" proba="1.0"></transition></state><state id="s4"><transition target="sX" action="epsilon" proba="1.0"></transition></state><state id="sX"><transition target="s0" action="epsilon" proba="1.0"></transition></state><state id="s0"><transition target="s3" action="org.quickserver.util.MyString.replaceAll(java.lang.String,java.lang.String,java.lang.String)" proba="0.07142857142857142"></transition><transition target="s1" action="org.quickserver.util.MyString.getStackTrace(java.lang.Throwable)" proba="0.7142857142857143"></transition><transition target="s2" action="org.quickserver.util.MyString.getMemInfo(float)" proba="0.21428571428571427"></transition></state><state id="s1"><transition target="s4" action="org.quickserver.util.MyString.getSystemInfo(java.lang.String)" proba="0.04"></transition><transition target="sX" action="epsilon" proba="0.36"></transition><transition target="s1" action="org.quickserver.util.MyString.getStackTrace(java.lang.Throwable)" proba="0.6"></transition></state><state id="s2"><transition target="sX" action="epsilon" proba="0.2727272727272727"></transition><transition target="s2" action="org.quickserver.util.MyString.getMemInfo(float)" proba="0.7272727272727273"></transition></state></states></ts>