<?xml version="1.0"?><ts><start>s0</start><states><state id="s3"><transition target="s3" action="java.lang.Object.toString()" proba="0.2222222222222222"></transition><transition target="sX" action="epsilon" proba="0.7777777777777778"></transition></state><state id="s4"><transition target="sX" action="epsilon" proba="1.0"></transition></state><state id="s5"><transition target="s6" action="java.lang.Object.copyTo(org.sat4j.specs.IVecInt)" proba="0.2"></transition><transition target="sX" action="epsilon" proba="0.8"></transition></state><state id="s6"><transition target="s7" action="java.lang.Object.push(int)" proba="1.0"></transition></state><state id="s7"><transition target="sX" action="epsilon" proba="1.0"></transition></state><state id="sX"><transition target="s0" action="epsilon" proba="1.0"></transition></state><state id="s0"><transition target="s3" action="java.lang.Object.toString()" proba="0.35"></transition><transition target="s4" action="java.lang.Object.hashCode()" proba="0.15"></transition><transition target="s5" action="java.lang.Object.equals(java.lang.Object)" proba="0.25"></transition><transition target="s1" action="java.lang.Object.getClass()" proba="0.25"></transition></state><state id="s1"><transition target="sX" action="epsilon" proba="0.8"></transition><transition target="s2" action="java.lang.Object.getName()" proba="0.2"></transition></state><state id="s2"><transition target="sX" action="epsilon" proba="1.0"></transition></state></states></ts>