<?xml version="1.0"?><ts><start>s0</start><states><state id="s3"><transition target="sX" action="epsilon" proba="0.5"></transition><transition target="s2" action="com.google.gson.FieldAttributes.fromString(java.lang.String)" proba="0.5"></transition></state><state id="s4"><transition target="s4" action="com.google.gson.FieldAttributes.hasModifier(int)" proba="0.8571428571428571"></transition><transition target="sX" action="epsilon" proba="0.14285714285714285"></transition></state><state id="s5"><transition target="sX" action="epsilon" proba="1.0"></transition></state><state id="s6"><transition target="sX" action="epsilon" proba="1.0"></transition></state><state id="s10"><transition target="sX" action="epsilon" proba="1.0"></transition></state><state id="s7"><transition target="s8" action="com.google.gson.FieldAttributes.getDeclaredClass()" proba="1.0"></transition></state><state id="sX"><transition target="s0" action="epsilon" proba="1.0"></transition></state><state id="s8"><transition target="sX" action="epsilon" proba="1.0"></transition></state><state id="s9"><transition target="sX" action="epsilon" proba="1.0"></transition></state><state id="s0"><transition target="s4" action="com.google.gson.FieldAttributes.hasModifier(int)" proba="0.03333333333333333"></transition><transition target="s5" action="com.google.gson.FieldAttributes.getDeclaringClass()" proba="0.03333333333333333"></transition><transition target="s6" action="com.google.gson.FieldAttributes.getAnnotation(java.lang.Class)" proba="0.03333333333333333"></transition><transition target="s10" action="com.google.gson.FieldAttributes.isSynthetic()" proba="0.03333333333333333"></transition><transition target="s7" action="com.google.gson.FieldAttributes.getDeclaredType()" proba="0.03333333333333333"></transition><transition target="s9" action="com.google.gson.FieldAttributes.getName()" proba="0.03333333333333333"></transition><transition target="s1" action="com.google.gson.FieldAttributes.&lt;init&gt;(java.lang.reflect.Field)" proba="0.36666666666666664"></transition><transition target="s2" action="com.google.gson.FieldAttributes.fromString(java.lang.String)" proba="0.43333333333333335"></transition></state><state id="s1"><transition target="s3" action="com.google.gson.FieldAttributes.getAnnotation(java.lang.Class&lt;T&gt;)" proba="0.4166666666666667"></transition><transition target="s4" action="com.google.gson.FieldAttributes.hasModifier(int)" proba="0.041666666666666664"></transition><transition target="s5" action="com.google.gson.FieldAttributes.getDeclaringClass()" proba="0.041666666666666664"></transition><transition target="s7" action="com.google.gson.FieldAttributes.getDeclaredType()" proba="0.041666666666666664"></transition><transition target="sX" action="epsilon" proba="0.25"></transition><transition target="s9" action="com.google.gson.FieldAttributes.getName()" proba="0.041666666666666664"></transition><transition target="s2" action="com.google.gson.FieldAttributes.fromString(java.lang.String)" proba="0.16666666666666666"></transition></state><state id="s2"><transition target="sX" action="epsilon" proba="0.4090909090909091"></transition><transition target="s1" action="com.google.gson.FieldAttributes.&lt;init&gt;(java.lang.reflect.Field)" proba="0.5909090909090909"></transition></state></states></ts>