<?xml version="1.0"?><ts><start>s0</start><states><state id="s3"><transition target="s4" action="org.junit.Assert.fail(java.lang.String)" proba="0.25"></transition><transition target="sX" action="epsilon" proba="0.75"></transition></state><state id="s4"><transition target="sX" action="epsilon" proba="1.0"></transition></state><state id="s5"><transition target="s4" action="org.junit.Assert.fail(java.lang.String)" proba="1.0"></transition></state><state id="sX"><transition target="s0" action="epsilon" proba="1.0"></transition></state><state id="s0"><transition target="s3" action="org.junit.Assert.assertNotNull(java.lang.Object)" proba="0.2857142857142857"></transition><transition target="s4" action="org.junit.Assert.fail(java.lang.String)" proba="0.07142857142857142"></transition><transition target="s5" action="org.junit.Assert.assertFalse(boolean)" proba="0.07142857142857142"></transition><transition target="s1" action="org.junit.Assert.assertTrue(boolean)" proba="0.35714285714285715"></transition><transition target="s2" action="org.junit.Assert.assertEquals(java.lang.Object,java.lang.Object)" proba="0.21428571428571427"></transition></state><state id="s1"><transition target="sX" action="epsilon" proba="0.07692307692307693"></transition><transition target="s1" action="org.junit.Assert.assertTrue(boolean)" proba="0.6153846153846154"></transition><transition target="s2" action="org.junit.Assert.assertEquals(java.lang.Object,java.lang.Object)" proba="0.3076923076923077"></transition></state><state id="s2"><transition target="sX" action="epsilon" proba="1.0"></transition></state></states></ts>