<?xml version="1.0"?><ts><start>s0</start><states><state id="s3"><transition target="sX" action="epsilon" proba="1.0"></transition></state><state id="s4"><transition target="sX" action="epsilon" proba="1.0"></transition></state><state id="s5"><transition target="sX" action="epsilon" proba="0.8"></transition><transition target="s12" action="java.lang.Math.min(int,int)" proba="0.2"></transition></state><state id="s6"><transition target="sX" action="epsilon" proba="1.0"></transition></state><state id="s7"><transition target="sX" action="epsilon" proba="1.0"></transition></state><state id="sX"><transition target="s0" action="epsilon" proba="1.0"></transition></state><state id="s8"><transition target="sX" action="epsilon" proba="1.0"></transition></state><state id="s9"><transition target="s13" action="java.lang.Math.max(int,int)" proba="0.5"></transition><transition target="sX" action="epsilon" proba="0.5"></transition></state><state id="s11"><transition target="s11" action="java.lang.Math.log(double)" proba="0.16666666666666666"></transition><transition target="sX" action="epsilon" proba="0.8333333333333334"></transition></state><state id="s10"><transition target="sX" action="epsilon" proba="1.0"></transition></state><state id="s13"><transition target="sX" action="epsilon" proba="1.0"></transition></state><state id="s12"><transition target="sX" action="epsilon" proba="1.0"></transition></state><state id="s15"><transition target="sX" action="epsilon" proba="1.0"></transition></state><state id="s14"><transition target="sX" action="epsilon" proba="1.0"></transition></state><state id="s0"><transition target="s3" action="java.lang.Math.sqrt(double)" proba="0.175"></transition><transition target="s4" action="java.lang.Math.pow(double,double)" proba="0.05"></transition><transition target="s5" action="java.lang.Math.abs(double)" proba="0.125"></transition><transition target="s6" action="java.lang.Math.cos(double)" proba="0.05"></transition><transition target="s7" action="java.lang.Math.ceil(double)" proba="0.05"></transition><transition target="s8" action="java.lang.Math.sin(double)" proba="0.05"></transition><transition target="s9" action="java.lang.Math.round(double)" proba="0.05"></transition><transition target="s11" action="java.lang.Math.log(double)" proba="0.125"></transition><transition target="s10" action="java.lang.Math.tan(double)" proba="0.05"></transition><transition target="s15" action="java.lang.Math.exp(double)" proba="0.05"></transition><transition target="s14" action="java.lang.Math.floor(double)" proba="0.075"></transition><transition target="s1" action="java.lang.Math.abs(int)" proba="0.075"></transition><transition target="s2" action="java.lang.Math.rint(double)" proba="0.075"></transition></state><state id="s1"><transition target="sX" action="epsilon" proba="1.0"></transition></state><state id="s2"><transition target="sX" action="epsilon" proba="1.0"></transition></state></states></ts>