<?xml version="1.0"?><ts><start>s0</start><states><state id="s3"><transition target="sX" action="epsilon" proba="1.0"></transition></state><state id="sX"><transition target="s0" action="epsilon" proba="1.0"></transition></state><state id="s0"><transition target="s1" action="weka.filters.unsupervised.attribute.PKIDiscretize.&lt;init&gt;()" proba="1.0"></transition></state><state id="s1"><transition target="s2" action="weka.filters.unsupervised.attribute.PKIDiscretize.setAttributeIndicesArray(int[])" proba="1.0"></transition></state><state id="s2"><transition target="s3" action="weka.filters.unsupervised.attribute.PKIDiscretize.getCapabilities()" proba="0.1978021978021978"></transition><transition target="sX" action="epsilon" proba="0.8021978021978022"></transition></state></states></ts>