<?xml version="1.0"?><ts><start>s0</start><states><state id="s3"><transition target="sX" action="epsilon" proba="1.0"></transition></state><state id="s4"><transition target="sX" action="epsilon" proba="1.0"></transition></state><state id="s5"><transition target="sX" action="epsilon" proba="1.0"></transition></state><state id="s6"><transition target="sX" action="epsilon" proba="1.0"></transition></state><state id="s7"><transition target="s6" action="java.sql.Statement.executeQuery(java.lang.String)" proba="1.0"></transition></state><state id="sX"><transition target="s0" action="epsilon" proba="1.0"></transition></state><state id="s8"><transition target="sX" action="epsilon" proba="1.0"></transition></state><state id="s9"><transition target="sX" action="epsilon" proba="1.0"></transition></state><state id="s11"><transition target="sX" action="epsilon" proba="1.0"></transition></state><state id="s10"><transition target="sX" action="epsilon" proba="1.0"></transition></state><state id="s12"><transition target="sX" action="epsilon" proba="1.0"></transition></state><state id="s0"><transition target="s3" action="java.sql.Statement.executeUpdate(java.lang.String)" proba="0.13636363636363635"></transition><transition target="s4" action="java.sql.Statement.executeUpdate(java.lang.String,java.lang.String[])" proba="0.045454545454545456"></transition><transition target="s5" action="java.sql.Statement.execute(java.lang.String,int)" proba="0.045454545454545456"></transition><transition target="s11" action="java.sql.Statement.executeBatch()" proba="0.045454545454545456"></transition><transition target="s6" action="java.sql.Statement.executeQuery(java.lang.String)" proba="0.22727272727272727"></transition><transition target="s10" action="java.sql.Statement.executeUpdate(java.lang.String,int)" proba="0.045454545454545456"></transition><transition target="s7" action="java.sql.Statement.setFetchSize(int)" proba="0.18181818181818182"></transition><transition target="s8" action="java.sql.Statement.execute(java.lang.String,java.lang.String[])" proba="0.045454545454545456"></transition><transition target="s12" action="java.sql.Statement.execute(java.lang.String,int[])" proba="0.045454545454545456"></transition><transition target="s9" action="java.sql.Statement.executeUpdate(java.lang.String,int[])" proba="0.045454545454545456"></transition><transition target="s1" action="java.sql.Statement.execute(java.lang.String)" proba="0.045454545454545456"></transition><transition target="s2" action="java.sql.Statement.close()" proba="0.09090909090909091"></transition></state><state id="s1"><transition target="sX" action="epsilon" proba="1.0"></transition></state><state id="s2"><transition target="sX" action="epsilon" proba="1.0"></transition></state></states></ts>