<?xml version="1.0"?><ts><start>s0</start><states><state id="s3"><transition target="s4" action="freemind.modes.NodeAdapter.getParentNode()" proba="1.0"></transition></state><state id="s4"><transition target="sX" action="epsilon" proba="1.0"></transition></state><state id="s5"><transition target="s6" action="freemind.modes.NodeAdapter.getActivatedHooks()" proba="1.0"></transition></state><state id="s6"><transition target="s7" action="freemind.modes.NodeAdapter.iterator()" proba="1.0"></transition></state><state id="s7"><transition target="sX" action="epsilon" proba="1.0"></transition></state><state id="sX"><transition target="s0" action="epsilon" proba="1.0"></transition></state><state id="s8"><transition target="s9" action="freemind.modes.NodeAdapter.setUserObject(java.lang.Object)" proba="1.0"></transition></state><state id="s9"><transition target="sX" action="epsilon" proba="1.0"></transition></state><state id="s11"><transition target="s12" action="freemind.modes.NodeAdapter.setItalic(boolean)" proba="1.0"></transition></state><state id="s10"><transition target="sX" action="epsilon" proba="1.0"></transition></state><state id="s13"><transition target="s14" action="freemind.modes.NodeAdapter.setBold(boolean)" proba="1.0"></transition></state><state id="s12"><transition target="sX" action="epsilon" proba="1.0"></transition></state><state id="s15"><transition target="s16" action="freemind.modes.NodeAdapter.setUnderlined(boolean)" proba="1.0"></transition></state><state id="s14"><transition target="sX" action="epsilon" proba="1.0"></transition></state><state id="s16"><transition target="sX" action="epsilon" proba="1.0"></transition></state><state id="s0"><transition target="s5" action="freemind.modes.NodeAdapter.getMap()" proba="0.14285714285714285"></transition><transition target="s11" action="freemind.modes.NodeAdapter.isItalic()" proba="0.14285714285714285"></transition><transition target="s10" action="freemind.modes.NodeAdapter.setLink(java.lang.String)" proba="0.14285714285714285"></transition><transition target="s13" action="freemind.modes.NodeAdapter.isBold()" proba="0.14285714285714285"></transition><transition target="s8" action="freemind.modes.NodeAdapter.toString()" proba="0.14285714285714285"></transition><transition target="s15" action="freemind.modes.NodeAdapter.isUnderlined()" proba="0.14285714285714285"></transition><transition target="s1" action="freemind.modes.NodeAdapter.setHGap(int)" proba="0.14285714285714285"></transition></state><state id="s1"><transition target="s2" action="freemind.modes.NodeAdapter.setShiftY(int)" proba="1.0"></transition></state><state id="s2"><transition target="s3" action="freemind.modes.NodeAdapter.isRoot()" proba="1.0"></transition></state></states></ts>